Workbook

Sheet Summary
A1: FY2026 budget vs actual vs forecast ($M)
A2: Company (HD or LOW) | B2: HD
A3: Favourable variance is positive: more revenue/profit, or lower operating expenses.
A5: Line | B5: Budget FY26 | C5: Actual H1 | D5: Forecast H2 | E5: Outlook FY26 | F5: Variance (fav +) | G5: Var % | H5: FY25 actual | I5: Outlook YoY % | K5: line key | L5: sign
A6: Revenue | B6: =SUMIFS(fact_pnl!$G$2:$G$141,fact_pnl!$A$2:$A$141,$B$2,fact_pnl!$E$2:$E$141,"Budget",fact_pnl!$C$2:$C$141,2026,fact_pnl!$F$2:$F$141,$K6) -> 170446.9 | C6: =SUMIFS(fact_pnl!$G$2:$G$141,fact_pnl!$A$2:$A$141,$B$2,fact_pnl!$E$2:$E$141,"Actual",fact_pnl!$C$2:$C$141,2026,fact_pnl!$F$2:$F$141,$K6,fact_pnl!$D$2:$D$141,"<=2") -> 89626 | D6: =SUMIFS(fact_pnl!$G$2:$G$141,fact_pnl!$A$2:$A$141,$B$2,fact_pnl!$E$2:$E$141,"Forecast",fact_pnl!$C$2:$C$141,2026,fact_pnl!$F$2:$F$141,$K6,fact_pnl!$D$2:$D$141,">=3") -> 80813.8 | E6: =C6+D6 -> 170439.8 | F6: =(E6-B6)*$L6 -> -7.1 | G6: =IF(B6=0,0,F6/B6) -> -4.1655202e-05 | H6: =SUMIFS(fact_pnl!$G$2:$G$141,fact_pnl!$A$2:$A$141,$B$2,fact_pnl!$E$2:$E$141,"Actual",fact_pnl!$C$2:$C$141,2025,fact_pnl!$F$2:$F$141,$K6) -> 164683 | I6: =IF(H6=0,0,E6/H6-1) -> 0.034956857 | K6: revenue | L6: 1
A7: Gross profit | B7: =SUMIFS(fact_pnl!$G$2:$G$141,fact_pnl!$A$2:$A$141,$B$2,fact_pnl!$E$2:$E$141,"Budget",fact_pnl!$C$2:$C$141,2026,fact_pnl!$F$2:$F$141,$K7) -> 56418 | C7: =SUMIFS(fact_pnl!$G$2:$G$141,fact_pnl!$A$2:$A$141,$B$2,fact_pnl!$E$2:$E$141,"Actual",fact_pnl!$C$2:$C$141,2026,fact_pnl!$F$2:$F$141,$K7,fact_pnl!$D$2:$D$141,"<=2") -> 29896 | D7: =SUMIFS(fact_pnl!$G$2:$G$141,fact_pnl!$A$2:$A$141,$B$2,fact_pnl!$E$2:$E$141,"Forecast",fact_pnl!$C$2:$C$141,2026,fact_pnl!$F$2:$F$141,$K7,fact_pnl!$D$2:$D$141,">=3") -> 26523.1 | E7: =C7+D7 -> 56419.1 | F7: =(E7-B7)*$L7 -> 1.1 | G7: =IF(B7=0,0,F7/B7) -> 1.9497324e-05 | H7: =SUMIFS(fact_pnl!$G$2:$G$141,fact_pnl!$A$2:$A$141,$B$2,fact_pnl!$E$2:$E$141,"Actual",fact_pnl!$C$2:$C$141,2025,fact_pnl!$F$2:$F$141,$K7) -> 54865 | I7: =IF(H7=0,0,E7/H7-1) -> 0.028325891 | K7: gross_profit | L7: 1
A8: Operating expenses | B8: =SUMIFS(fact_pnl!$G$2:$G$141,fact_pnl!$A$2:$A$141,$B$2,fact_pnl!$E$2:$E$141,"Budget",fact_pnl!$C$2:$C$141,2026,fact_pnl!$F$2:$F$141,$K8) -> 35112 | C8: =SUMIFS(fact_pnl!$G$2:$G$141,fact_pnl!$A$2:$A$141,$B$2,fact_pnl!$E$2:$E$141,"Actual",fact_pnl!$C$2:$C$141,2026,fact_pnl!$F$2:$F$141,$K8,fact_pnl!$D$2:$D$141,"<=2") -> 18076 | D8: =SUMIFS(fact_pnl!$G$2:$G$141,fact_pnl!$A$2:$A$141,$B$2,fact_pnl!$E$2:$E$141,"Forecast",fact_pnl!$C$2:$C$141,2026,fact_pnl!$F$2:$F$141,$K8,fact_pnl!$D$2:$D$141,">=3") -> 17605.6 | E8: =C8+D8 -> 35681.6 | F8: =(E8-B8)*$L8 -> -569.6 | G8: =IF(B8=0,0,F8/B8) -> -0.016222374 | H8: =SUMIFS(fact_pnl!$G$2:$G$141,fact_pnl!$A$2:$A$141,$B$2,fact_pnl!$E$2:$E$141,"Actual",fact_pnl!$C$2:$C$141,2025,fact_pnl!$F$2:$F$141,$K8) -> 33975 | I8: =IF(H8=0,0,E8/H8-1) -> 0.050231052 | K8: opex | L8: -1
A9: Operating income | B9: =SUMIFS(fact_pnl!$G$2:$G$141,fact_pnl!$A$2:$A$141,$B$2,fact_pnl!$E$2:$E$141,"Budget",fact_pnl!$C$2:$C$141,2026,fact_pnl!$F$2:$F$141,$K9) -> 21305.9 | C9: =SUMIFS(fact_pnl!$G$2:$G$141,fact_pnl!$A$2:$A$141,$B$2,fact_pnl!$E$2:$E$141,"Actual",fact_pnl!$C$2:$C$141,2026,fact_pnl!$F$2:$F$141,$K9,fact_pnl!$D$2:$D$141,"<=2") -> 11820 | D9: =SUMIFS(fact_pnl!$G$2:$G$141,fact_pnl!$A$2:$A$141,$B$2,fact_pnl!$E$2:$E$141,"Forecast",fact_pnl!$C$2:$C$141,2026,fact_pnl!$F$2:$F$141,$K9,fact_pnl!$D$2:$D$141,">=3") -> 8917.5 | E9: =C9+D9 -> 20737.5 | F9: =(E9-B9)*$L9 -> -568.4 | G9: =IF(B9=0,0,F9/B9) -> -0.026678056 | H9: =SUMIFS(fact_pnl!$G$2:$G$141,fact_pnl!$A$2:$A$141,$B$2,fact_pnl!$E$2:$E$141,"Actual",fact_pnl!$C$2:$C$141,2025,fact_pnl!$F$2:$F$141,$K9) -> 20890 | I9: =IF(H9=0,0,E9/H9-1) -> -0.0073001436 | K9: operating_income | L9: 1
A10: Net income | B10: =SUMIFS(fact_pnl!$G$2:$G$141,fact_pnl!$A$2:$A$141,$B$2,fact_pnl!$E$2:$E$141,"Budget",fact_pnl!$C$2:$C$141,2026,fact_pnl!$F$2:$F$141,$K10) -> 14387.3 | C10: =SUMIFS(fact_pnl!$G$2:$G$141,fact_pnl!$A$2:$A$141,$B$2,fact_pnl!$E$2:$E$141,"Actual",fact_pnl!$C$2:$C$141,2026,fact_pnl!$F$2:$F$141,$K10,fact_pnl!$D$2:$D$141,"<=2") -> 8055 | D10: =SUMIFS(fact_pnl!$G$2:$G$141,fact_pnl!$A$2:$A$141,$B$2,fact_pnl!$E$2:$E$141,"Forecast",fact_pnl!$C$2:$C$141,2026,fact_pnl!$F$2:$F$141,$K10,fact_pnl!$D$2:$D$141,">=3") -> 5880 | E10: =C10+D10 -> 13935 | F10: =(E10-B10)*$L10 -> -452.3 | G10: =IF(B10=0,0,F10/B10) -> -0.031437448 | H10: =SUMIFS(fact_pnl!$G$2:$G$141,fact_pnl!$A$2:$A$141,$B$2,fact_pnl!$E$2:$E$141,"Actual",fact_pnl!$C$2:$C$141,2025,fact_pnl!$F$2:$F$141,$K10) -> 14156 | I10: =IF(H10=0,0,E10/H10-1) -> -0.015611755 | K10: net_income | L10: 1
A12: Gross margin % | B12: =IF(B6=0,0,B7/B6) -> 0.33100045 | C12: =IF(C6=0,0,C7/C6) -> 0.33356392 | D12: =IF(D6=0,0,D7/D6) -> 0.32820013 | E12: =IF(E6=0,0,E7/E6) -> 0.33102069 | F12: =(E12-B12)*10000 -> 0.20242356 | H12: =IF(H6=0,0,H7/H6) -> 0.33315521
A13: Operating margin % | B13: =IF(B6=0,0,B9/B6) -> 0.12500022 | C13: =IF(C6=0,0,C9/C6) -> 0.13188137 | D13: =IF(D6=0,0,D9/D6) -> 0.11034625 | E13: =IF(E6=0,0,E9/E6) -> 0.12167053 | F13: =(E13-B13)*10000 -> -33.296947 | H13: =IF(H6=0,0,H9/H6) -> 0.12684977
A15: Sign column (L) is an input: +1 where more is better, -1 for costs. Source data: SEC XBRL companyfacts; budget and forecast drivers on the 'assumptions' sheet.

Sheet fact_pnl
A1: ticker | B1: period_key | C1: fiscal_year | D1: fq | E1: scenario | F1: line | G1: amount_musd
A2: HD | B2: FY25 Q1 | C2: 2025 | D2: 1 | E2: Actual | F2: gross_profit | G2: 13459
A3: HD | B3: FY25 Q1 | C3: 2025 | D3: 1 | E3: Actual | F3: net_income | G3: 3433
A4: HD | B4: FY25 Q1 | C4: 2025 | D4: 1 | E4: Actual | F4: operating_income | G4: 5133
A5: HD | B5: FY25 Q1 | C5: 2025 | D5: 1 | E5: Actual | F5: opex | G5: 8326
A6: HD | B6: FY25 Q1 | C6: 2025 | D6: 1 | E6: Actual | F6: revenue | G6: 39856
A7: HD | B7: FY25 Q2 | C7: 2025 | D7: 2 | E7: Actual | F7: gross_profit | G7: 15125
A8: HD | B8: FY25 Q2 | C8: 2025 | D8: 2 | E8: Actual | F8: net_income | G8: 4551
A9: HD | B9: FY25 Q2 | C9: 2025 | D9: 2 | E9: Actual | F9: operating_income | G9: 6555
A10: HD | B10: FY25 Q2 | C10: 2025 | D10: 2 | E10: Actual | F10: opex | G10: 8570
A11: HD | B11: FY25 Q2 | C11: 2025 | D11: 2 | E11: Actual | F11: revenue | G11: 45277
A12: HD | B12: FY25 Q3 | C12: 2025 | D12: 3 | E12: Actual | F12: gross_profit | G12: 13815
A13: HD | B13: FY25 Q3 | C13: 2025 | D13: 3 | E13: Actual | F13: net_income | G13: 3601
... A141: LOW | B141: FY26 Q4 | C141: 2026 | D141: 4 | E141: Forecast | F141: revenue | G141: 20585

Sheet dim_company
A1: ticker | B1: company | C1: fiscal_year_end | D1: fy2025_acquisition | E1: acquisition_close | F1: sec_cik
A2: HD | B2: The Home Depot | C2: Sunday nearest 31 Jan | D2: GMS Inc. | E2: 2025-09-04 | F2: 0000354950
A3: LOW | B3: Lowe's Companies | C3: Friday nearest 31 Jan | D3: Foundation Building Materials | E3: 2025-10-09 | F3: 0000060667

Sheet dim_line
A1: line | B1: line_label | C1: line_sort | D1: sign
A2: revenue | B2: Revenue | C2: 1 | D2: 1
A3: gross_profit | B3: Gross profit | C3: 2 | D3: 1
A4: opex | B4: Operating expenses | C4: 3 | D4: -1
A5: operating_income | B5: Operating income | C5: 4 | D5: 1
A6: net_income | B6: Net income | C6: 5 | D6: 1

Sheet dim_period
A1: period_key | B1: fiscal_year | C1: fq | D1: quarter | E1: period_sort | F1: status
A2: FY25 Q1 | B2: 2025 | C2: 1 | D2: Q1 | E2: 20251 | F2: Prior year
A3: FY25 Q2 | B3: 2025 | C3: 2 | D3: Q2 | E3: 20252 | F3: Prior year
A4: FY25 Q3 | B4: 2025 | C4: 3 | D4: Q3 | E4: 20253 | F4: Prior year
A5: FY25 Q4 | B5: 2025 | C5: 4 | D5: Q4 | E5: 20254 | F5: Prior year
A6: FY26 Q1 | B6: 2026 | C6: 1 | D6: Q1 | E6: 20261 | F6: Actual
A7: FY26 Q2 | B7: 2026 | C7: 2 | D7: Q2 | E7: 20262 | F7: Actual
A8: FY26 Q3 | B8: 2026 | C8: 3 | D8: Q3 | E8: 20263 | F8: Forecast
A9: FY26 Q4 | B9: 2026 | C9: 4 | D9: Q4 | E9: 20264 | F9: Forecast

Sheet dim_scenario
A1: scenario | B1: scenario_sort
A2: Actual | B2: 1
A3: Budget | B3: 2
A4: Forecast | B4: 3

Sheet commentary
A1: ticker | B1: rank | C1: direction | D1: line_label | E1: period | F1: variance_musd | G1: explanation
A2: HD | B2: 1 | C2: Favourable | D2: Revenue | E2: FY26 Q2 | F2: 999 | G2: Q2 revenue beat budget by $1.00B (+2.1%); H1 by $1.51B. Mostly phasing, not outperformance: the budget uses FY2025's quarterly shape, and GMS only joined on 4 Sep 2025, so FY2025's first half had no GMS revenue. Comparable sales were +1.7% in Q2. The full-year revenue outlook is $170.44B, on budget, so the H1 beat is expected to reverse in H2.
A3: HD | B3: 2 | C3: Unfavourable | D3: Operating expenses | E3: FY26 H1 | F3: -616 | G3: Opex ran $0.62B over budget in H1 (+3.5%) while revenue was only +1.7% over. Opex grew 7.0% year over year against 5.3% revenue growth, which is consistent with carrying GMS's cost base. It absorbed the whole gross-profit beat: operating income is $0.57B under budget for the year and the operating margin outlook is 12.2%, against 12.5% budget and 12.4-12.6% guidance. Action: hold H2 SG&A growth at or below revenue growth to protect the guided margin.
A4: HD | B4: 3 | C4: Unfavourable | D4: Revenue | E4: FY26 Q4 | F4: -955 | G4: Q4 revenue is forecast $0.95B below budget. This is the mirror image of the H1 phasing: the FY2025 Q4 base already includes GMS, so growth falls to the +1% comp driver. Treat H1 and Q4 together, not as separate surprises.
A5: LOW | B5: 1 | C5: Favourable | D5: Revenue | E5: FY26 Q1 | F5: 520 | G5: Q1 revenue beat budget by $0.52B (+2.3%). FBM closed on 9 Oct 2025, so it is in FY2026 Q1 but absent from the FY2025 Q1 base the budget was phased on. Underlying demand is soft: comparable sales were +0.2% in Q2.
A6: LOW | B6: 2 | C6: Unfavourable | D6: Revenue | E6: FY26 Q4 | F6: -1601 | G6: Q4 revenue is forecast $1.60B below budget, the largest variance in the model. The $93.0B budget needed about +6% H2 growth; with FBM fully in the FY2025 Q4 base and comp guidance cut to flat, the forecast H2 growth is +2.9%. Full-year outlook is $91.64B ($1.36B under budget), close to Lowe's own lowered $92.0B outlook (19 Aug 2026). Action: rebase the H2 budget to the updated outlook.
A7: LOW | B7: 3 | C7: Unfavourable | D7: Gross profit | E7: FY26 Q2 | F7: -154 | G7: Q2 gross margin was 33.0% against 33.8% budget ($0.15B). A lower-margin mix from pro distribution businesses is a plausible driver but is not disclosed separately. Carried into H2, gross profit is $1.11B under budget and the operating margin outlook is 11.0% against 11.3% budget. The 'favourable' opex in H2 is a derived-line effect of lower revenue, not cost savings.

Sheet assumptions
A1: driver | B1: HD | C1: LOW | D1: source
A2: Budget revenue | B2: +3.5% on FY2025 (midpoint of 2.5-4.5%) | C2: $93.0B (midpoint of $92.0-94.0B) | D2: Company FY2026 guidance, 24/25 Feb 2026
A3: Budget gross margin | B3: 33.1% (guided) | C3: 33.5% = FY2025 actual (not guided) | D3: HD guidance; LOW analyst assumption
A4: Budget operating margin (GAAP) | B4: 12.5% (midpoint 12.4-12.6%) | C4: 11.3% (midpoint 11.2-11.4%) | D4: Company guidance
A5: Net interest | B5: $2.3B, 1/4 per quarter | C5: $1.6B, 1/4 per quarter | D5: Company guidance
A6: Tax rate | B6: 24.3% | C6: 24.5% | D6: Company guidance
A7: Quarterly phasing | B7: FY2025 quarter shares | C7: FY2025 quarter shares | D7: Known limitation: acquisitions closed mid-FY2025, so H1 is under-phased
A8: Forecast comp driver (Q3-Q4) | B8: +1.0% (flat to +2.0%, reaffirmed 18 Aug 2026) | C8: 0.0% (cut to flat, 19 Aug 2026) | D8: Q2 FY2026 releases
A9: Q3 acquisition stub | B9: GMS $5,513.7M x 31/365 = $468M | C9: FBM ~$6.5B x 68/365 = $1,211M | D9: GMS FY2025 release (18 Jun 2025); FBM pro forma revenue per MDM
A10: Forecast margins | B10: Budget quarter margin + H1 gap (conservative) | C10: Budget quarter margin + H1 gap (conservative) | D10: Analyst assumption
A11: Grain | B11: Quarterly | C11: Quarterly | D11: Public filings are quarterly; monthly splits would be fabricated

Sheet checks
A1: check_name | B1: ticker | C1: pass
A2: Budget op margin = guided op margin | B2: HD | C2: =TRUE() -> TRUE
A3: Budget op margin = guided op margin | B3: LOW | C3: =TRUE() -> TRUE
A4: Budget revenue ties to guided FY revenue | B4: HD | C4: =TRUE() -> TRUE
A5: Budget revenue ties to guided FY revenue | B5: LOW | C5: =TRUE() -> TRUE
A6: Every 2026 quarter has budget and forecast for all 5 lines | B6: HD | C6: =TRUE() -> TRUE
A7: Every 2026 quarter has budget and forecast for all 5 lines | B7: LOW | C7: =TRUE() -> TRUE
A8: FY2025 quarters sum to 10-K full year (within $5M rounding) | B8: HD | C8: =TRUE() -> TRUE
A9: FY2025 quarters sum to 10-K full year (within $5M rounding) | B9: LOW | C9: =TRUE() -> TRUE
A10: Forecast Q1-Q2 equals actual | B10: HD | C10: =TRUE() -> TRUE
A11: Forecast Q1-Q2 equals actual | B11: LOW | C11: =TRUE() -> TRUE
A12: Opex = gross profit - operating income, all scenarios | B12: HD | C12: =TRUE() -> TRUE
A13: Opex = gross profit - operating income, all scenarios | B13: LOW | C13: =TRUE() -> TRUE
